login/__init__.py
login/admin.py
login/apps.py
login/forms.py
login/models.py
login/tests.py
login/views.py
login/migrations/__init__.py
login/static/login/css/login.css
login/static/login/css/register.css
login/templates/login/confirm.html
login/templates/login/index.html
login/templates/login/login-old.html
login/templates/login/login.html
login/templates/login/login_old2.html
login/templates/login/register.html
django_first-1.0.dist-info/LICENSE
django_first-1.0.dist-info/METADATA
django_first-1.0.dist-info/WHEEL
django_first-1.0.dist-info/top_level.txt
django_first-1.0.dist-info/RECORD
